Homevee/API.py
Homevee/CloudConnection.py
Homevee/CloudConnection_NEW.py
Homevee/CommandLine.py
Homevee/SmartSpeakerConnection.py
Homevee/__init__.py
Homevee/AIAgents/__init__.py
Homevee/AIAgents/ImageClassifier/ARControl.py
Homevee/AIAgents/ImageClassifier/PeopleClassifier.py
Homevee/AIAgents/ImageClassifier/__init__.py
Homevee/Cronjob/CalendarReminderCronjob.py
Homevee/Cronjob/CheckUpdateCronjob.py
Homevee/Cronjob/HeatingSchemeCronjob.py
Homevee/Cronjob/OverviewNotificationCronjob.py
Homevee/Cronjob/PhilipsHueValueLoaderCronjob.py
Homevee/Cronjob/SaveEnergyDataCronjob.py
Homevee/Cronjob/SaveSensorDataCronjob.py
Homevee/Cronjob/UserPingCronjob.py
Homevee/Cronjob/WeatherUpdaterCronjob.py
Homevee/Cronjob/ZWaveValueLoaderCronjob.py
Homevee/Cronjob/__init__.py
Homevee/Cronjob/run_automations.py
Homevee/Cronjob/video_surveillance.py
Homevee/DeviceAPI/__init__.py
Homevee/DeviceAPI/blind_control.py
Homevee/DeviceAPI/dimmer.py
Homevee/DeviceAPI/energy_data.py
Homevee/DeviceAPI/get_modes.py
Homevee/DeviceAPI/heating.py
Homevee/DeviceAPI/kodi_api.py
Homevee/DeviceAPI/max_cube_control.py
Homevee/DeviceAPI/mqtt_api.py
Homevee/DeviceAPI/mqtt_sensor.py
Homevee/DeviceAPI/rfid_control.py
Homevee/DeviceAPI/rgb_control.py
Homevee/DeviceAPI/set_modes.py
Homevee/DeviceAPI/toggle_devices.py
Homevee/DeviceAPI/wake_on_lan.py
Homevee/DeviceAPI/xbox_wol.py
Homevee/DeviceAPI/max_cube/__init__.py
Homevee/DeviceAPI/miyo_cube/__init__.py
Homevee/DeviceAPI/philips_hue/__init__.py
Homevee/DeviceAPI/rademacher_homepilot/__init__.py
Homevee/DeviceAPI/rademacher_homepilot/blinds_control.py
Homevee/DeviceAPI/rademacher_homepilot/set_modes.py
Homevee/DeviceAPI/zwave/__init__.py
Homevee/DeviceAPI/zwave/device_control.py
Homevee/DeviceAPI/zwave/get_devices.py
Homevee/DeviceAPI/zwave/get_rooms.py
Homevee/DeviceAPI/zwave/utils.py
Homevee/Exception/__init__.py
Homevee/Functions/__init__.py
Homevee/Functions/ar_control.py
Homevee/Functions/calendar.py
Homevee/Functions/chat.py
Homevee/Functions/events.py
Homevee_Dev-0.0.0.0.dist-info/METADATA
Homevee_Dev-0.0.0.0.dist-info/WHEEL
Homevee_Dev-0.0.0.0.dist-info/entry_points.txt
Homevee_Dev-0.0.0.0.dist-info/top_level.txt
Homevee_Dev-0.0.0.0.dist-info/RECORD
